srtseg/__init__.py
srtseg/adaptors.py
srtseg/srtcut.py
srtseg/srtseg.py
srtseg-0.5.0.dist-info/LICENSE
srtseg-0.5.0.dist-info/METADATA
srtseg-0.5.0.dist-info/WHEEL
srtseg-0.5.0.dist-info/top_level.txt
srtseg-0.5.0.dist-info/RECORD
