Metadata-Version: 2.1
Name: srtseg
Version: 0.5.0
Summary: Extend srt by splitting the videos
Home-page: https://github.com/jianshuo/srtseg
Author: Jianshuo Wang
Author-email: Jianshuo Wang <jianshuo@hotmail.com>
Project-URL: Homepage, https://github.com/jianshuo/srtseg
Project-URL: Issues, https://github.com/jianshuo/srtseg/issues
Classifier: Programming Language :: Python :: 3
Classifier: License :: OSI Approved :: MIT License
Classifier: Operating System :: OS Independent
Requires-Python: >=3.10
License-File: LICENSE
